obsplus/__init__.py
obsplus/constants.py
obsplus/exceptions.py
obsplus/interfaces.py
obsplus/version.py
obsplus/bank/__init__.py
obsplus/bank/core.py
obsplus/bank/eventbank.py
obsplus/bank/stationbank.py
obsplus/bank/wavebank.py
obsplus/datasets/__init__.py
obsplus/datasets/bingham_test.py
obsplus/datasets/crandall_test.py
obsplus/datasets/dataset.py
obsplus/datasets/default_test.py
obsplus/datasets/ta_test.py
obsplus/datasets/bingham_test/dataset_hash.json
obsplus/datasets/bingham_test/dataset_version.txt
obsplus/datasets/bingham_test/events.xml
obsplus/datasets/bingham_test/inventory.xml
obsplus/datasets/crandall_test/dataset_hash.json
obsplus/datasets/crandall_test/dataset_version.txt
obsplus/datasets/crandall_test/events.xml
obsplus/datasets/default_test/dataset_hash.json
obsplus/datasets/default_test/dataset_version.txt
obsplus/datasets/ta_test/dataset_hash.json
obsplus/datasets/ta_test/dataset_version.txt
obsplus/datasets/ta_test/inventory.xml
obsplus/events/__init__.py
obsplus/events/get_events.py
obsplus/events/json.py
obsplus/events/merge.py
obsplus/events/pd.py
obsplus/events/schema.py
obsplus/events/validate.py
obsplus/stations/__init__.py
obsplus/stations/get_stations.py
obsplus/stations/pd.py
obsplus/structures/__init__.py
obsplus/structures/dfextractor.py
obsplus/structures/fetcher.py
obsplus/utils/__init__.py
obsplus/utils/bank.py
obsplus/utils/dataset.py
obsplus/utils/docs.py
obsplus/utils/events.py
obsplus/utils/geodetics.py
obsplus/utils/misc.py
obsplus/utils/mseed.py
obsplus/utils/pd.py
obsplus/utils/stations.py
obsplus/utils/testing.py
obsplus/utils/time.py
obsplus/utils/validate.py
obsplus/utils/waveforms.py
obsplus/waveforms/__init__.py
obsplus/waveforms/get_waveforms.py
obsplus-0.3.2.dist-info/licenses/LICENSE
obsplus-0.3.2.dist-info/METADATA
obsplus-0.3.2.dist-info/WHEEL
obsplus-0.3.2.dist-info/entry_points.txt
obsplus-0.3.2.dist-info/top_level.txt
obsplus-0.3.2.dist-info/RECORD
