Metadata-Version: 2.4
Name: obsplus
Version: 0.3.2
Summary: An ObsPy exapanson pack
Author-email: Derrick Chambers <d-chambers@users.noreply.github.com>, Shawn Boltz <sboltz@users.noreply.github.com>
License:                    GNU LESSER GENERAL PUBLIC LICENSE
Project-URL: Bug Tracker, https://github.com/niosh-mining/obsplus/issues
Project-URL: Documentation, https://github.com/niosh-mining/obsplus
Project-URL: Homepage, https://github.com/niosh-mining/obsplus
Keywords: geophysics,Seismology
Classifier: Development Status :: 4 - Beta
Classifier: License :: OSI Approved :: GNU Lesser General Public License v3 or later (LGPLv3+)
Classifier: Topic :: Scientific/Engineering
Classifier: Programming Language :: Python :: 3.10
Classifier: Programming Language :: Python :: 3.11
Classifier: Programming Language :: Python :: 3.12
Requires-Python: >=3.10
License-File: LICENSE
Requires-Dist: numpy<2.0,>1.24.4
Requires-Dist: obspy>=1.4.0
Requires-Dist: pandas>=1.0
Requires-Dist: progressbar2
Requires-Dist: pydantic<3.0,>=2.0
Requires-Dist: scipy
Requires-Dist: tables
Requires-Dist: typing-extensions
Provides-Extra: docs
Requires-Dist: sphinx>=1.5.1; extra == "docs"
Requires-Dist: ipykernel; extra == "docs"
Requires-Dist: numpydoc; extra == "docs"
Requires-Dist: sphinx_autodoc_typehints; extra == "docs"
Requires-Dist: nbsphinx; extra == "docs"
Requires-Dist: sphinx-automodapi; extra == "docs"
Requires-Dist: jinja2; extra == "docs"
Requires-Dist: typer; extra == "docs"
Provides-Extra: test
Requires-Dist: pytest; extra == "test"
Requires-Dist: coverage<5.0; extra == "test"
Requires-Dist: pytest-cov; extra == "test"
Requires-Dist: coveralls; extra == "test"
Requires-Dist: nbval; extra == "test"
Requires-Dist: twine; extra == "test"
Requires-Dist: pre-commit; extra == "test"
Provides-Extra: dev
Requires-Dist: obsplus[test]; extra == "dev"
Requires-Dist: obsplus[docs]; extra == "dev"
Dynamic: license-file
